paella/__init__.py
paella/parallel/__init__.py
paella/parallel/modules.py
paella/parallel/train.py
paella/parallel/utils.py
paella/parallel/vqgan.py
paella/parallel/run/run.sh
paella/single/__init__.py
paella/single/modules.py
paella/single/train.py
paella/single/utils.py
paella/single/vqgan.py
paella/utils/alter_attention.py
paella/utils/modules.py
paella-0.0.1.dev1.dist-info/LICENSE
paella-0.0.1.dev1.dist-info/METADATA
paella-0.0.1.dev1.dist-info/WHEEL
paella-0.0.1.dev1.dist-info/top_level.txt
paella-0.0.1.dev1.dist-info/RECORD
