Metadata-Version: 2.1
Name: paella
Version: 0.0.1.dev1
Summary: paella - Fast Text-Conditional Discrete Denoising on Vector-Quantized Latent Spaces
Author: Juncong Moo
Keywords: paella
Classifier: Programming Language :: Python :: 3
Classifier: Programming Language :: Python :: 3.8
Classifier: Programming Language :: Python :: 3.9
Classifier: Programming Language :: Python :: 3.10
License-File: LICENSE
Requires-Dist: tqdm
Requires-Dist: wandb
Requires-Dist: numpy
Requires-Dist: torch
Requires-Dist: Pillow
Requires-Dist: requests
Requires-Dist: matplotlib
Requires-Dist: torchvision
Requires-Dist: transformers
Requires-Dist: open-clip-torch
Requires-Dist: warmup-scheduler
